pwdlib/__init__.py
pwdlib/_hash.py
pwdlib/exceptions.py
pwdlib/py.typed
pwdlib/hashers/__init__.py
pwdlib/hashers/argon2.py
pwdlib/hashers/base.py
pwdlib/hashers/bcrypt.py
pwdlib-0.1.0.dist-info/METADATA
pwdlib-0.1.0.dist-info/WHEEL
pwdlib-0.1.0.dist-info/licenses/LICENSE
pwdlib-0.1.0.dist-info/RECORD
