Metadata-Version: 2.1
Name: pwdlib
Version: 0.1.0
Summary: Modern password hashing for Python
Project-URL: Documentation, https://frankie567.github.io/pwdlib/
Project-URL: Source, https://github.com/frankie567/pwdlib
Author-email: pwdlib <fvoron@gmail.com>
License-File: LICENSE
Classifier: Development Status :: 4 - Beta
Classifier: Intended Audience :: Developers
Classifier: License :: OSI Approved :: MIT License
Classifier: Programming Language :: Python :: 3 :: Only
Classifier: Programming Language :: Python :: 3.8
Classifier: Programming Language :: Python :: 3.9
Classifier: Programming Language :: Python :: 3.10
Classifier: Programming Language :: Python :: 3.11
Classifier: Programming Language :: Python :: 3.12
Classifier: Topic :: Security
Classifier: Topic :: Security :: Cryptography
Requires-Python: >=3.8
Provides-Extra: argon2
Requires-Dist: argon2-cffi==23.1.0; extra == 'argon2'
Provides-Extra: bcrypt
Requires-Dist: bcrypt==4.1.2; extra == 'bcrypt'
